{
  "wordList": [
    {
      "word": "ingrodd",
      "correct": "djupt rotad",
      "distractors": ["tillfällig", "nyväckt", "ytlig"],
      "difficulty": 3
    },
    {
      "word": "ingripande",
      "correct": "genomgripande",
      "distractors": ["obetydlig", "varsam", "kortvarig"],
      "difficulty": 2
    },
    {
      "word": "inhägnad",
      "correct": "omgiven av stängsel",
      "distractors": ["öppen för alla", "belägen inomhus", "svår att hitta"],
      "difficulty": 2
    },
    {
      "word": "initiativrik",
      "correct": "företagsam",
      "distractors": ["avvaktande", "trögrörlig", "osjälvständig"],
      "difficulty": 2
    },
    {
      "word": "inkapslad",
      "correct": "innesluten",
      "distractors": ["utbredd", "synliggjord", "frilagd"],
      "difficulty": 2
    },
    {
      "word": "inkorrekt",
      "correct": "felaktig",
      "distractors": ["noggrann", "artigt hållen", "fullständig"],
      "difficulty": 1
    },
    {
      "word": "inkörd",
      "correct": "inarbetad",
      "distractors": ["provisorisk", "oförberedd", "överdriven"],
      "difficulty": 2
    },
    {
      "word": "innersta",
      "correct": "djupaste",
      "distractors": ["yttersta", "översta", "synligaste"],
      "difficulty": 1
    },
    {
      "word": "innovativ",
      "correct": "nyskapande",
      "distractors": ["gammaldags", "regelstyrd", "förutsägbar"],
      "difficulty": 1
    },
    {
      "word": "inskjuten",
      "correct": "infogad",
      "distractors": ["utelämnad", "försenad", "särskild"],
      "difficulty": 3
    },
    {
      "word": "insmickrande",
      "correct": "inställsam",
      "distractors": ["avvisande", "rättfram", "kortfattad"],
      "difficulty": 2
    },
    {
      "word": "insnöad",
      "correct": "alltför fixerad vid",
      "distractors": ["överraskad av", "fri från", "skeptisk till"],
      "difficulty": 2
    },
    {
      "word": "inspirerad",
      "correct": "uppfylld av idéer",
      "distractors": ["tung i sinnet", "helt opåverkad", "osäker på sig själv"],
      "difficulty": 1
    },
    {
      "word": "instängd",
      "correct": "inspärrad",
      "distractors": ["välkomnad", "kringresande", "osynlig"],
      "difficulty": 1
    },
    {
      "word": "instämmande",
      "correct": "medhållande",
      "distractors": ["ifrågasättande", "likgiltig", "förvirrad"],
      "difficulty": 1
    },
    {
      "word": "intakt",
      "correct": "oskadad",
      "distractors": ["sliten", "sönderdelad", "ofullständig"],
      "difficulty": 1
    },
    {
      "word": "integritetsfull",
      "correct": "principfast",
      "distractors": ["eftergiven", "närgången", "vankelmodig"],
      "difficulty": 3
    },
    {
      "word": "intressant",
      "correct": "fängslande",
      "distractors": ["likgiltig", "enformig", "obetydlig"],
      "difficulty": 1
    },
    {
      "word": "intim",
      "correct": "mycket nära",
      "distractors": ["offentligt visad", "formellt ordnad", "långvarigt uppskjuten"],
      "difficulty": 1
    },
    {
      "word": "intrigant",
      "correct": "ränksmidande",
      "distractors": ["hjälpsam", "okomplicerad", "rättrådig"],
      "difficulty": 4
    },
    {
      "word": "invand",
      "correct": "van",
      "distractors": ["ovillig", "tillfällig", "oförmögen"],
      "difficulty": 3
    },
    {
      "word": "inventiv",
      "correct": "uppfinningsrik",
      "distractors": ["regelbunden", "färglös", "senfärdig"],
      "difficulty": 2
    },
    {
      "word": "ironifri",
      "correct": "allvarlig",
      "distractors": ["skämtsam", "sarkastisk", "dubbeltydig"],
      "difficulty": 3
    },
    {
      "word": "iserad",
      "correct": "täckt av is",
      "distractors": ["täckt av sand", "fri från frost", "uppvärmd"],
      "difficulty": 4
    },
    {
      "word": "ja",
      "correct": "instämmande svar",
      "distractors": ["avvisande besked", "tveksamt uttalande", "hånfull kommentar"],
      "difficulty": 1
    },
    {
      "word": "jordbunden",
      "correct": "realistisk",
      "distractors": ["dagdrömmande", "högtravande", "storslagen"],
      "difficulty": 2
    },
    {
      "word": "jublande",
      "correct": "mycket glad",
      "distractors": ["djupt besviken", "kallt avmätt", "oroligt tveksam"],
      "difficulty": 1
    },
    {
      "word": "juridisk",
      "correct": "rättslig",
      "distractors": ["medicinsk", "språklig", "historisk"],
      "difficulty": 1
    },
    {
      "word": "justerbar",
      "correct": "möjlig att ändra",
      "distractors": ["svår att nå", "avsedd att låsas", "färdig att kassera"],
      "difficulty": 1
    },
    {
      "word": "jäktad",
      "correct": "stressad",
      "distractors": ["utvilad", "obetymrad", "långsam"],
      "difficulty": 1
    },
    {
      "word": "jämnmodig",
      "correct": "lugn",
      "distractors": ["lättretlig", "uppjagad", "modstulen"],
      "difficulty": 3
    },
    {
      "word": "järv",
      "correct": "modig",
      "distractors": ["försagd", "foglig", "varsam"],
      "difficulty": 2
    },
    {
      "word": "kalkylerad",
      "correct": "uträknad",
      "distractors": ["spontan", "slumpmässig", "omtumlande"],
      "difficulty": 2
    },
    {
      "word": "kanonisk",
      "correct": "erkänd som auktoritativ",
      "distractors": ["tveksamt belagd", "förbjuden av kyrkan", "nyligen påhittad"],
      "difficulty": 4
    },
    {
      "word": "kapriciös",
      "correct": "nyckfull",
      "distractors": ["pålitlig", "återhållsam", "lågmäld"],
      "difficulty": 4
    },
    {
      "word": "karismatisk",
      "correct": "utstrålningsfull",
      "distractors": ["färglös", "tillknäppt", "osmidig"],
      "difficulty": 2
    },
    {
      "word": "karv",
      "correct": "sträv",
      "distractors": ["len", "översvallande", "mild"],
      "difficulty": 4
    },
    {
      "word": "kastvindig",
      "correct": "oförutsägbar",
      "distractors": ["stadig", "ordnad", "tålmodig"],
      "difficulty": 3
    },
    {
      "word": "kaxig",
      "correct": "stöddig",
      "distractors": ["blyg", "undergiven", "hövlig"],
      "difficulty": 1
    },
    {
      "word": "kedjad",
      "correct": "fastbunden",
      "distractors": ["frisläppt", "upphöjd", "förskjuten"],
      "difficulty": 2
    },
    {
      "word": "klangfull",
      "correct": "resonant",
      "distractors": ["hes", "stum", "pressad"],
      "difficulty": 2
    },
    {
      "word": "klargörande",
      "correct": "förtydligande",
      "distractors": ["förvillande", "överslätande", "upprepande"],
      "difficulty": 1
    },
    {
      "word": "klassisk",
      "correct": "tidlös",
      "distractors": ["övergående", "omoderniserad", "slarvig"],
      "difficulty": 1
    },
    {
      "word": "klentrogen",
      "correct": "skeptisk",
      "distractors": ["lättlurad", "entusiastisk", "förtrolig"],
      "difficulty": 3
    },
    {
      "word": "klibbig",
      "correct": "seg och vidhäftande",
      "distractors": ["torr och smulig", "hård och blank", "luftig och lätt"],
      "difficulty": 1
    },
    {
      "word": "klinisk",
      "correct": "steril",
      "distractors": ["hemtrevlig", "bullrig", "smutsig"],
      "difficulty": 2
    },
    {
      "word": "klipsk",
      "correct": "smart",
      "distractors": ["trögtänkt", "glömsk", "fumlig"],
      "difficulty": 1
    },
    {
      "word": "klok",
      "correct": "förnuftig",
      "distractors": ["naiv", "fåfäng", "obetänksam"],
      "difficulty": 1
    },
    {
      "word": "knapp",
      "correct": "begränsad",
      "distractors": ["överflödande", "märkbar", "utförlig"],
      "difficulty": 1
    },
    {
      "word": "knotig",
      "correct": "knölig",
      "distractors": ["slät", "rak", "fuktig"],
      "difficulty": 2
    },
    {
      "word": "knusslig",
      "correct": "småaktig",
      "distractors": ["givmild", "storsint", "självklar"],
      "difficulty": 3
    },
    {
      "word": "kolerisk",
      "correct": "lättretlig",
      "distractors": ["tålmodig", "mild", "resignerad"],
      "difficulty": 3
    },
    {
      "word": "kompakt",
      "correct": "tät",
      "distractors": ["gles", "utspridd", "skrymmande"],
      "difficulty": 1
    },
    {
      "word": "kompatibel",
      "correct": "förenlig",
      "distractors": ["oförenlig", "osäker", "överlägsen"],
      "difficulty": 2
    },
    {
      "word": "kompetent",
      "correct": "skicklig",
      "distractors": ["obevandrad", "långsam", "osäker"],
      "difficulty": 1
    },
    {
      "word": "komplex",
      "correct": "sammansatt",
      "distractors": ["enkel", "ytlig", "enhetlig"],
      "difficulty": 2
    },
    {
      "word": "komponerad",
      "correct": "samlad",
      "distractors": ["uppjagad", "spretig", "otålig"],
      "difficulty": 3
    },
    {
      "word": "komprometterad",
      "correct": "skadad i anseende",
      "distractors": ["högt aktad", "nyutnämnd", "obemärkt"],
      "difficulty": 4
    },
    {
      "word": "konfrontativ",
      "correct": "stridslysten",
      "distractors": ["undvikande", "medgörlig", "försynt"],
      "difficulty": 3
    },
    {
      "word": "kongenial",
      "correct": "själsbesläktad",
      "distractors": ["oense", "ytlig", "underordnad"],
      "difficulty": 4
    },
    {
      "word": "konjunktiv",
      "correct": "verbform för önskan",
      "distractors": ["substantiv för person", "tecken för paus", "regel för stavning"],
      "difficulty": 4
    },
    {
      "word": "konstitutiv",
      "correct": "grundläggande",
      "distractors": ["tillfällig", "oväsentlig", "påhittad"],
      "difficulty": 4
    },
    {
      "word": "konstruktiv",
      "correct": "uppbygglig",
      "distractors": ["förstörande", "undvikande", "fientlig"],
      "difficulty": 2
    },
    {
      "word": "konsumtiv",
      "correct": "förbrukande",
      "distractors": ["skapande", "sparande", "förnyande"],
      "difficulty": 4
    },
    {
      "word": "kontemplativ",
      "correct": "begrundande",
      "distractors": ["hetsig", "utåtriktad", "hänsynslös"],
      "difficulty": 4
    },
    {
      "word": "kontrollerad",
      "correct": "behärskad",
      "distractors": ["utlevande", "spontan", "orolig"],
      "difficulty": 1
    },
    {
      "word": "konvergent",
      "correct": "sammanstrålande",
      "distractors": ["utåtgående", "tillbakadragande", "splittrande"],
      "difficulty": 4
    },
    {
      "word": "konvex",
      "correct": "välvd utåt",
      "distractors": ["välvd inåt", "helt kantig", "slätpressad"],
      "difficulty": 4
    },
    {
      "word": "korpulent",
      "correct": "kraftig",
      "distractors": ["spenslig", "snabbfotad", "nervös"],
      "difficulty": 3
    },
    {
      "word": "korstågsaktig",
      "correct": "missionerande",
      "distractors": ["likgiltig", "försonlig", "vardaglig"],
      "difficulty": 4
    },
    {
      "word": "kortfattad",
      "correct": "koncis",
      "distractors": ["vidlyftig", "svävande", "omständig"],
      "difficulty": 1
    },
    {
      "word": "kosmisk",
      "correct": "som rör universum",
      "distractors": ["som rör hushållet", "som rör kroppen", "som rör juridiken"],
      "difficulty": 3
    },
    {
      "word": "kraftlös",
      "correct": "svag",
      "distractors": ["energisk", "stabil", "fyndig"],
      "difficulty": 1
    },
    {
      "word": "krallig",
      "correct": "muskulös",
      "distractors": ["spenslig", "tankspridd", "gänglig"],
      "difficulty": 2
    },
    {
      "word": "krampaktig",
      "correct": "spänd",
      "distractors": ["avslappnad", "naturlig", "mjuk"],
      "difficulty": 2
    },
    {
      "word": "krigisk",
      "correct": "stridslysten",
      "distractors": ["fredlig", "obetydlig", "lågmäld"],
      "difficulty": 2
    },
    {
      "word": "krispig",
      "correct": "frasig",
      "distractors": ["sladdrig", "seg", "smetig"],
      "difficulty": 1
    },
    {
      "word": "krusig",
      "correct": "lockig",
      "distractors": ["rak", "nerrakad", "spretig"],
      "difficulty": 2
    },
    {
      "word": "kry",
      "correct": "frisk",
      "distractors": ["sjuklig", "sömnig", "överkänslig"],
      "difficulty": 2
    },
    {
      "word": "kryptisk",
      "correct": "svårtolkad",
      "distractors": ["övertydlig", "öppenhjärtig", "vardaglig"],
      "difficulty": 3
    }
  ],
  "wordDetails": {
    "ingrodd": {
      "explanation": "\"ingrodd\" betyder ungefär \"djupt rotad\".",
      "example": "Misstron mellan grupperna var så ingrodd att samtalen gick trögt."
    },
    "ingripande": {
      "explanation": "\"ingripande\" betyder ungefär \"genomgripande\".",
      "example": "Reformen innebar en ingripande förändring av hela systemet."
    },
    "inhägnad": {
      "explanation": "\"inhägnad\" betyder ungefär \"omgiven av stängsel\".",
      "example": "Fåren gick i en inhägnad hage bakom ladan."
    },
    "initiativrik": {
      "explanation": "\"initiativrik\" betyder ungefär \"företagsam\".",
      "example": "Den initiativrika studenten ordnade snabbt en lösning på problemet."
    },
    "inkapslad": {
      "explanation": "\"inkapslad\" betyder ungefär \"innesluten\".",
      "example": "Fyndet låg inkapslat i ett tjockt lager av lera."
    },
    "inkorrekt": {
      "explanation": "\"inkorrekt\" betyder ungefär \"felaktig\".",
      "example": "Artikeln byggde på en inkorrekt uppgift om händelseförloppet."
    },
    "inkörd": {
      "explanation": "\"inkörd\" betyder ungefär \"inarbetad\".",
      "example": "Efter några veckor var hon helt inkörd i de nya rutinerna."
    },
    "innersta": {
      "explanation": "\"innersta\" betyder ungefär \"djupaste\".",
      "example": "Han delade sina innersta tankar med sin närmaste vän."
    },
    "innovativ": {
      "explanation": "\"innovativ\" betyder ungefär \"nyskapande\".",
      "example": "Företaget belönades för sin innovativa lösning på energiproblemet."
    },
    "inskjuten": {
      "explanation": "\"inskjuten\" betyder ungefär \"infogad\".",
      "example": "Mitt i texten fanns en inskjuten kommentar från redaktören."
    },
    "insmickrande": {
      "explanation": "\"insmickrande\" betyder ungefär \"inställsam\".",
      "example": "Hans insmickrande ton gjorde flera i rummet misstänksamma."
    },
    "insnöad": {
      "explanation": "\"insnöad\" betyder ungefär \"alltför fixerad vid\".",
      "example": "Han blev så insnöad på detaljer att helheten försvann."
    },
    "inspirerad": {
      "explanation": "\"inspirerad\" betyder ungefär \"uppfylld av idéer\".",
      "example": "Efter utställningen kände hon sig ovanligt inspirerad."
    },
    "instängd": {
      "explanation": "\"instängd\" betyder ungefär \"inspärrad\".",
      "example": "Han kände sig instängd i den lilla lägenheten hela vintern."
    },
    "instämmande": {
      "explanation": "\"instämmande\" betyder ungefär \"medhållande\".",
      "example": "Publiken nickade instämmande när talaren sammanfattade läget."
    },
    "intakt": {
      "explanation": "\"intakt\" betyder ungefär \"oskadad\".",
      "example": "Det gamla brevet låg fortfarande intakt i lådan."
    },
    "integritetsfull": {
      "explanation": "\"integritetsfull\" betyder ungefär \"principfast\".",
      "example": "Hon uppfattades som integritetsfull och svår att påverka med påtryckningar."
    },
    "intressant": {
      "explanation": "\"intressant\" betyder ungefär \"fängslande\".",
      "example": "Föreläsningen var så intressant att ingen tittade på klockan."
    },
    "intim": {
      "explanation": "\"intim\" betyder ungefär \"mycket nära\".",
      "example": "De hade ett intimt samtal långt efter att de andra gått hem."
    },
    "intrigant": {
      "explanation": "\"intrigant\" betyder ungefär \"ränksmidande\".",
      "example": "I romanen framställs hovmannen som en intrigant figur."
    },
    "invand": {
      "explanation": "\"invand\" betyder ungefär \"van\".",
      "example": "Hon var invand vid långa arbetsdagar och tog pressen med ro."
    },
    "inventiv": {
      "explanation": "\"inventiv\" betyder ungefär \"uppfinningsrik\".",
      "example": "Barnen var inventiva och byggde en koja av nästan ingenting."
    },
    "ironifri": {
      "explanation": "\"ironifri\" betyder ungefär \"allvarlig\".",
      "example": "Hans ironifria svar gjorde att ingen riktigt visste om han skämtade tidigare."
    },
    "iserad": {
      "explanation": "\"iserad\" betyder ungefär \"täckt av is\".",
      "example": "Räcket var iserat efter nattens kyla och mycket halt."
    },
    "ja": {
      "explanation": "\"ja\" betyder ungefär \"instämmande svar\".",
      "example": "Ett tydligt ja i omröstningen gav förslaget stöd."
    },
    "jordbunden": {
      "explanation": "\"jordbunden\" betyder ungefär \"realistisk\".",
      "example": "Trots stora visioner var hon jordbunden i sina bedömningar."
    },
    "jublande": {
      "explanation": "\"jublande\" betyder ungefär \"mycket glad\".",
      "example": "Laget möttes av jublande supportrar på torget."
    },
    "juridisk": {
      "explanation": "\"juridisk\" betyder ungefär \"rättslig\".",
      "example": "Företaget sökte juridisk hjälp inför förhandlingen."
    },
    "justerbar": {
      "explanation": "\"justerbar\" betyder ungefär \"möjlig att ändra\".",
      "example": "Stolen har en justerbar rygg som passar olika användare."
    },
    "jäktad": {
      "explanation": "\"jäktad\" betyder ungefär \"stressad\".",
      "example": "Hon såg jäktad ut när hon kom springande till mötet."
    },
    "jämnmodig": {
      "explanation": "\"jämnmodig\" betyder ungefär \"lugn\".",
      "example": "Han förblev jämnmodig trots den hårda kritiken."
    },
    "järv": {
      "explanation": "\"järv\" betyder ungefär \"modig\".",
      "example": "Det var ett järvt beslut att satsa allt på den nya idén."
    },
    "kalkylerad": {
      "explanation": "\"kalkylerad\" betyder ungefär \"uträknad\".",
      "example": "Hela manövern var ett kalkylerat försök att vinna tid."
    },
    "kanonisk": {
      "explanation": "\"kanonisk\" betyder ungefär \"erkänd som auktoritativ\".",
      "example": "Texten räknas som kanonisk inom den religiösa traditionen."
    },
    "kapriciös": {
      "explanation": "\"kapriciös\" betyder ungefär \"nyckfull\".",
      "example": "Hennes kapriciösa humör gjorde planeringen svår."
    },
    "karismatisk": {
      "explanation": "\"karismatisk\" betyder ungefär \"utstrålningsfull\".",
      "example": "Den karismatiske ledaren fick snabbt hela salen med sig."
    },
    "karv": {
      "explanation": "\"karv\" betyder ungefär \"sträv\".",
      "example": "Vinet hade en karv eftersmak som inte alla uppskattade."
    },
    "kastvindig": {
      "explanation": "\"kastvindig\" betyder ungefär \"oförutsägbar\".",
      "example": "Hans kastvindiga humör gjorde kollegorna osäkra."
    },
    "kaxig": {
      "explanation": "\"kaxig\" betyder ungefär \"stöddig\".",
      "example": "Hon svarade med en kaxig kommentar och log."
    },
    "kedjad": {
      "explanation": "\"kedjad\" betyder ungefär \"fastbunden\".",
      "example": "Cykeln stod kedjad vid staketet utanför huset."
    },
    "klangfull": {
      "explanation": "\"klangfull\" betyder ungefär \"resonant\".",
      "example": "Han läste dikten med en klangfull röst."
    },
    "klargörande": {
      "explanation": "\"klargörande\" betyder ungefär \"förtydligande\".",
      "example": "Lärarens klargörande kommentar gjorde uppgiften lättare."
    },
    "klassisk": {
      "explanation": "\"klassisk\" betyder ungefär \"tidlös\".",
      "example": "Den svarta kappan har en klassisk form som aldrig riktigt går ur tiden."
    },
    "klentrogen": {
      "explanation": "\"klentrogen\" betyder ungefär \"skeptisk\".",
      "example": "Hon var klentrogen till löftena om snabba förbättringar."
    },
    "klibbig": {
      "explanation": "\"klibbig\" betyder ungefär \"seg och vidhäftande\".",
      "example": "Bordet blev klibbigt av den utspillda saften."
    },
    "klinisk": {
      "explanation": "\"klinisk\" betyder ungefär \"steril\".",
      "example": "Rummet var så kliniskt rent att det nästan kändes opersonligt."
    },
    "klipsk": {
      "explanation": "\"klipsk\" betyder ungefär \"smart\".",
      "example": "Det var klipskt av henne att spara alla kvitton."
    },
    "klok": {
      "explanation": "\"klok\" betyder ungefär \"förnuftig\".",
      "example": "Det klokaste vore att vänta tills vi vet mer."
    },
    "knapp": {
      "explanation": "\"knapp\" betyder ungefär \"begränsad\".",
      "example": "Tiden var knapp, så mötet fick hållas kort."
    },
    "knotig": {
      "explanation": "\"knotig\" betyder ungefär \"knölig\".",
      "example": "Den gamla eken hade en knotig stam."
    },
    "knusslig": {
      "explanation": "\"knusslig\" betyder ungefär \"småaktig\".",
      "example": "Han var knusslig med detaljer och släppte inget förbi."
    },
    "kolerisk": {
      "explanation": "\"kolerisk\" betyder ungefär \"lättretlig\".",
      "example": "Chefen var kolerisk och tappade lätt humöret."
    },
    "kompakt": {
      "explanation": "\"kompakt\" betyder ungefär \"tät\".",
      "example": "Publiken stod kompakt framför scenen."
    },
    "kompatibel": {
      "explanation": "\"kompatibel\" betyder ungefär \"förenlig\".",
      "example": "Programvaran är kompatibel med de flesta äldre system."
    },
    "kompetent": {
      "explanation": "\"kompetent\" betyder ungefär \"skicklig\".",
      "example": "Hon är en mycket kompetent projektledare."
    },
    "komplex": {
      "explanation": "\"komplex\" betyder ungefär \"sammansatt\".",
      "example": "Frågan är mer komplex än den först verkar."
    },
    "komponerad": {
      "explanation": "\"komponerad\" betyder ungefär \"samlad\".",
      "example": "Trots anklagelserna förblev hon komponerad."
    },
    "komprometterad": {
      "explanation": "\"komprometterad\" betyder ungefär \"skadad i anseende\".",
      "example": "Efter avslöjandet var hans ställning i bolaget komprometterad."
    },
    "konfrontativ": {
      "explanation": "\"konfrontativ\" betyder ungefär \"stridslysten\".",
      "example": "Debatten blev onödigt konfrontativ redan från start."
    },
    "kongenial": {
      "explanation": "\"kongenial\" betyder ungefär \"själsbesläktad\".",
      "example": "Översättningen ansågs vara kongenial med originalets ton."
    },
    "konjunktiv": {
      "explanation": "\"konjunktiv\" betyder ungefär \"verbform för önskan\".",
      "example": "I äldre svenska förekommer konjunktiv oftare än i dag."
    },
    "konstitutiv": {
      "explanation": "\"konstitutiv\" betyder ungefär \"grundläggande\".",
      "example": "Förtroende är en konstitutiv del av allt samarbete."
    },
    "konstruktiv": {
      "explanation": "\"konstruktiv\" betyder ungefär \"uppbygglig\".",
      "example": "Kritiken var skarp men ändå konstruktiv."
    },
    "konsumtiv": {
      "explanation": "\"konsumtiv\" betyder ungefär \"förbrukande\".",
      "example": "Verksamheten var konsumtiv och skapade inga nya resurser."
    },
    "kontemplativ": {
      "explanation": "\"kontemplativ\" betyder ungefär \"begrundande\".",
      "example": "Hon satt i ett kontemplativt lugn och såg ut över sjön."
    },
    "kontrollerad": {
      "explanation": "\"kontrollerad\" betyder ungefär \"behärskad\".",
      "example": "Hans kontrollerade tonfall lugnade gruppen."
    },
    "konvergent": {
      "explanation": "\"konvergent\" betyder ungefär \"sammanstrålande\".",
      "example": "Linjerna är konvergenta och möts längre fram i bilden."
    },
    "konvex": {
      "explanation": "\"konvex\" betyder ungefär \"välvd utåt\".",
      "example": "Spegeln hade en konvex yta som fick rummet att verka större."
    },
    "korpulent": {
      "explanation": "\"korpulent\" betyder ungefär \"kraftig\".",
      "example": "Den korpulente mannen tog plats längst fram i salen."
    },
    "korstågsaktig": {
      "explanation": "\"korstågsaktig\" betyder ungefär \"missionerande\".",
      "example": "Hans korstågsaktiga ton gjorde debatten mer laddad."
    },
    "kortfattad": {
      "explanation": "\"kortfattad\" betyder ungefär \"koncis\".",
      "example": "Rapporten var kortfattad men tydlig."
    },
    "kosmisk": {
      "explanation": "\"kosmisk\" betyder ungefär \"som rör universum\".",
      "example": "Forskaren beskrev de kosmiska processerna bakom stjärnornas liv."
    },
    "kraftlös": {
      "explanation": "\"kraftlös\" betyder ungefär \"svag\".",
      "example": "Efter febern kände hon sig kraftlös i flera dagar."
    },
    "krallig": {
      "explanation": "\"krallig\" betyder ungefär \"muskulös\".",
      "example": "Den kralliga vakten stod vid entrén hela kvällen."
    },
    "krampaktig": {
      "explanation": "\"krampaktig\" betyder ungefär \"spänd\".",
      "example": "Hans leende såg krampaktigt ut under intervjun."
    },
    "krigisk": {
      "explanation": "\"krigisk\" betyder ungefär \"stridslysten\".",
      "example": "Retoriken blev allt mer krigisk ju längre mötet pågick."
    },
    "krispig": {
      "explanation": "\"krispig\" betyder ungefär \"frasig\".",
      "example": "Brödet var fortfarande varmt och krispigt."
    },
    "krusig": {
      "explanation": "\"krusig\" betyder ungefär \"lockig\".",
      "example": "Hon borstade sitt krusiga hår framför spegeln."
    },
    "kry": {
      "explanation": "\"kry\" betyder ungefär \"frisk\".",
      "example": "Efter några dagars vila kände han sig äntligen kry igen."
    },
    "kryptisk": {
      "explanation": "\"kryptisk\" betyder ungefär \"svårtolkad\".",
      "example": "Meddelandet var så kryptiskt att ingen begrep vad hon menade."
    }
  }
}
